{
  "project_info": {
    "project_number": "925519887542",
    "project_id": "ayam-nina",
    "storage_bucket": "ayam-nina.firebasestorage.app"
  },
  "client": [
    {
      "client_info": {
        "mobilesdk_app_id": "1:925519887542:android:7450d7e723898e4ad1fa17",
        "android_client_info": {
          "package_name": "com.example.kedai_ayam_nina"
        }
      },
      "oauth_client": [],
      "api_key": [
        {
          "current_key": "AIzaSyAJt_LDVPyDfEsTERB6nNReNfvoHWttwvI"
        }
      ],
      "services": {
        "appinvite_service": {
          "other_platform_oauth_client": []
        }
      }
    }
  ],
  "configuration_version": "1"
}